guardrails_detector_huggingface/__init__.py
guardrails_detector_huggingface/app.py
guardrails_detector_huggingface/detector.py
guardrails_detector_huggingface/scheme.py
guardrails_detector_huggingface-0.1.1.dist-info/METADATA
guardrails_detector_huggingface-0.1.1.dist-info/WHEEL
guardrails_detector_huggingface-0.1.1.dist-info/licenses/LICENSE
guardrails_detector_huggingface-0.1.1.dist-info/RECORD
